setup.py
flask_simple_logger/__init__.py
flask_simple_logger.egg-info/PKG-INFO
flask_simple_logger.egg-info/SOURCES.txt
flask_simple_logger.egg-info/dependency_links.txt
flask_simple_logger.egg-info/requires.txt
flask_simple_logger.egg-info/top_level.txt