Metadata-Version: 1.0
Name: flask-simple-logger
Version: 0.0.2
Summary: flask logger
Home-page: UNKNOWN
Author: UNKNOWN
Author-email: UNKNOWN
License: UNKNOWN
Platform: UNKNOWN
